xotl/plato/__init__.py
xotl/plato/_version.py
xotl/plato/base.py
xotl/plato/py.typed
xotl/plato/release.py
xotl/plato/schema.py
xotl/plato/testing.py
xotl/plato/types.py
xotl_plato-2.0.0.dist-info/METADATA
xotl_plato-2.0.0.dist-info/WHEEL
xotl_plato-2.0.0.dist-info/licenses/LICENSE
xotl_plato-2.0.0.dist-info/RECORD
