Metadata-Version: 2.1
Name: xotl.plato
Version: 2.0.0
Summary: Basic (non-recursive) 'platonic' schemata
Author-email: "Merchise Autrement [~º/~]" <info@merchise.de>
License-Expression: MIT
License-File: LICENSE
Requires-Python: >=3.8
Requires-Dist: backports-zoneinfo; python_version < '3.9'
Requires-Dist: hypothesis<7.0,>=6.30
Requires-Dist: immutables>=0.20
Requires-Dist: typing-extensions; python_version < '3.9'
Requires-Dist: tzdata
Requires-Dist: xotl-tools<4.0,>=2.2.5; python_version <= '3.11'
Requires-Dist: xotl-tools<4.0,>=3.0.0; python_version > '3.11'
Requires-Dist: xotless<5.0,>=3.8.0; python_version <= '3.11'
Requires-Dist: xotless<5.0,>=4.0.0; python_version > '3.11'
